Blauwal3_Survival_Analysis-0.6.1-py3.10-nspkg.pth
orangecontrib/survival_analysis/__init__.py
orangecontrib/survival_analysis/i18n_config.py
orangecontrib/survival_analysis/evaluation/__init__.py
orangecontrib/survival_analysis/evaluation/scoring.py
orangecontrib/survival_analysis/locale/survival_analysis.de.yml
orangecontrib/survival_analysis/locale/survival_analysis.en.yml
orangecontrib/survival_analysis/locale/survival_analysis.zh.yml
orangecontrib/survival_analysis/modeling/__init__.py
orangecontrib/survival_analysis/modeling/cox.py
orangecontrib/survival_analysis/tests/__init__.py
orangecontrib/survival_analysis/widgets/__init__.py
orangecontrib/survival_analysis/widgets/data.py
orangecontrib/survival_analysis/widgets/owassurvivaldata.py
orangecontrib/survival_analysis/widgets/owchorts.py
orangecontrib/survival_analysis/widgets/owcoxregression.py
orangecontrib/survival_analysis/widgets/owkaplanmeier.py
orangecontrib/survival_analysis/widgets/owranksurvivalfeatures.py
orangecontrib/survival_analysis/widgets/owstepwisecoxregression.py
orangecontrib/survival_analysis/widgets/owsurvivalnomogram.py
orangecontrib/survival_analysis/widgets/icons/owassurvivaldata.svg
orangecontrib/survival_analysis/widgets/icons/owcohorts.svg
orangecontrib/survival_analysis/widgets/icons/owcoxregression.svg
orangecontrib/survival_analysis/widgets/icons/owkaplanmeier.svg
orangecontrib/survival_analysis/widgets/icons/owranksurvivalfeatures.svg
orangecontrib/survival_analysis/widgets/icons/owstepwisecoxregression.svg
orangecontrib/survival_analysis/widgets/icons/owsurvivalnomogram.svg
orangecontrib/survival_analysis/widgets/icons/survival_analysis_category.svg
orangecontrib/survival_analysis/widgets/tests/__init__.py
orangecontrib/survival_analysis/widgets/tests/test_owassurvivaldata.py
orangecontrib/survival_analysis/widgets/tests/test_owkaplanmeier.py
orangecontrib/survival_analysis/widgets/tests/test_owsurvivalnomogram.py
Blauwal3_Survival_Analysis-0.6.1.dist-info/LICENSE
Blauwal3_Survival_Analysis-0.6.1.dist-info/METADATA
Blauwal3_Survival_Analysis-0.6.1.dist-info/WHEEL
Blauwal3_Survival_Analysis-0.6.1.dist-info/entry_points.txt
Blauwal3_Survival_Analysis-0.6.1.dist-info/namespace_packages.txt
Blauwal3_Survival_Analysis-0.6.1.dist-info/top_level.txt
Blauwal3_Survival_Analysis-0.6.1.dist-info/RECORD
