Metadata-Version: 2.1
Name: Blauwal3-Survival-Analysis
Version: 0.6.1
Summary: 蓝鲸数据挖掘软件包的生存分析附加组件。
Home-page: https://github.com/biolab/orange3-survival-analysis
Author: 大圣实验楼
Author-email: dashenglab@163.com
License: GPL3+
Project-URL: Bug Tracker, https://github.com/biolab/orange3-survival-analysis/issues
Project-URL: Source Code, https://github.com/biolab/orange3-survival-analysis/
Keywords: 'orange3 add-on'
Requires-Python: >=3.9
License-File: LICENSE
Requires-Dist: Blauwal3>=3.34.0
Requires-Dist: lifelines
Requires-Dist: statsmodels
Provides-Extra: doc
Requires-Dist: sphinx; extra == "doc"
Requires-Dist: recommonmark; extra == "doc"
Requires-Dist: sphinx-rtd-theme; extra == "doc"
Provides-Extra: test
Requires-Dist: pytest; extra == "test"
Requires-Dist: coverage; extra == "test"
Requires-Dist: flake8; extra == "test"
Requires-Dist: flake8-bugbear; extra == "test"
Requires-Dist: black; extra == "test"
